plotting/__init__.py
plotting/base.py
plotting/colormaps.py
plotting/dataframes.py
plotting/points.py
plotting/version.py
plotting-0.0.7.dist-info/LICENSE
plotting-0.0.7.dist-info/METADATA
plotting-0.0.7.dist-info/WHEEL
plotting-0.0.7.dist-info/top_level.txt
plotting-0.0.7.dist-info/RECORD
