Metadata-Version: 2.1
Name: plotting
Version: 0.0.7
Summary: UNKNOWN
Home-page: UNKNOWN
Author: Michael Rossol
Author-email: mrossol@gmail.com
License: BSD license
Keywords: rev
Platform: UNKNOWN
Classifier: Development Status :: 4 - Beta
Classifier: Intended Audience :: Science/Research
Classifier: License :: OSI Approved :: BSD License
Classifier: Natural Language :: English
Classifier: Programming Language :: Python :: 3.6
Classifier: Programming Language :: Python :: 3.7
Classifier: Programming Language :: Python :: 3.8
Provides-Extra: dev
